polish_your_prompt/__init__.py
polish_your_prompt/core/__init__.py
polish_your_prompt/core/refiner.py
polish_your_prompt/core/types.py
polish_your_prompt/llm/__init__.py
polish_your_prompt/llm/open_ai.py
polish_your_prompt/schemas/APE.py
polish_your_prompt/schemas/BROKE.py
polish_your_prompt/schemas/CARE.py
polish_your_prompt/schemas/CHAT.py
polish_your_prompt/schemas/COSTAR.py
polish_your_prompt/schemas/CREATE.py
polish_your_prompt/schemas/CRISPE.py
polish_your_prompt/schemas/ERA.py
polish_your_prompt/schemas/ICIO.py
polish_your_prompt/schemas/RACE.py
polish_your_prompt/schemas/RISE.py
polish_your_prompt/schemas/ROSES.py
polish_your_prompt/schemas/RTF.py
polish_your_prompt/schemas/TAG.py
polish_your_prompt/schemas/TRACE.py
polish_your_prompt/schemas/__init__.py
polish_your_prompt/schemas/schema.py
polish_your_prompt/templates/__init__.py
polish_your_prompt/templates/annotated_refiner_prefix.py
polish_your_prompt/templates/schema_refiner_prefix.py
polish_your_prompt/templates/simple_refiner_prefix.py
polish_your_prompt/templates/template.py
polish_your_prompt/utils/__init__.py
polish_your_prompt/utils/json_extractor.py
polish_your_prompt-0.0.2.dist-info/LICENSE
polish_your_prompt-0.0.2.dist-info/METADATA
polish_your_prompt-0.0.2.dist-info/WHEEL
polish_your_prompt-0.0.2.dist-info/top_level.txt
polish_your_prompt-0.0.2.dist-info/RECORD
