Metadata-Version: 2.1
Name: polish_your_prompt
Version: 0.0.2
Summary: Make anyone master of prompt engineering.
Home-page: https://github.com/ChenZiHong-Gavin/Polish-Your-Prompt
Author: chenzihong_gavin
Author-email: chenzihong_gavin@foxmail.com
License: MIT
Classifier: License :: OSI Approved :: MIT License
Classifier: Programming Language :: Python
Classifier: Programming Language :: Python :: 3
Classifier: Programming Language :: Python :: 3.6
Classifier: Programming Language :: Python :: Implementation :: CPython
Classifier: Programming Language :: Python :: Implementation :: PyPy
Requires-Python: >=3.9.0
License-File: LICENSE
Requires-Dist: openai ==0.28.0
Requires-Dist: tiktoken
Requires-Dist: retry
Requires-Dist: python-dotenv
